kp_fraydit/__init__.py
kp_fraydit/admin.py
kp_fraydit/custom_errors.py
kp_fraydit/custom_types.py
kp_fraydit/datetime_functions.py
kp_fraydit/metaclasses.py
kp_fraydit/root.py
kp_fraydit/schema_client.py
kp_fraydit/connections/DEPRECATED-connection_settings.py
kp_fraydit/connections/__init__.py
kp_fraydit/connections/connection.py
kp_fraydit/connections/connection_observer.py
kp_fraydit/connections/misc.py
kp_fraydit/connectors/__init__.py
kp_fraydit/connectors/connector.py
kp_fraydit/financial/__init__.py
kp_fraydit/financial/price_connector.py
kp_fraydit/logs/__init__.py
kp_fraydit/producers/__init__.py
kp_fraydit/producers/log_producer.py
kp_fraydit/producers/producer.py
kp_fraydit/schemas/__init__.py
kp_fraydit-0.1.15.dist-info/LICENSE
kp_fraydit-0.1.15.dist-info/METADATA
kp_fraydit-0.1.15.dist-info/WHEEL
kp_fraydit-0.1.15.dist-info/top_level.txt
kp_fraydit-0.1.15.dist-info/RECORD
