Metadata-Version: 2.1
Name: kp-fraydit
Version: 0.1.15
Summary: Kafka library for producing and consuming
Home-page: https://fraydit.com
Author: Jamey Harris
Author-email: jameycharris@yahoo.com
License: UNKNOWN
Project-URL: Bug Tracker, https://github.com/coldicefisher/kp_fraydit/
Platform: UNKNOWN
Classifier: Programming Language :: Python :: 3
Classifier: License :: OSI Approved :: MIT License
Classifier: Operating System :: OS Independent
Requires-Python: >=3.6
License-File: LICENSE
